czech_air_quality/__init__.py
czech_air_quality/api.py
czech_air_quality/const.py
czech_air_quality/data_manager.py
czech_air_quality/exceptions.py
czech_air_quality/processing.py
czech_air_quality-2.0.1.dist-info/licenses/LICENSE
czech_air_quality-2.0.1.dist-info/METADATA
czech_air_quality-2.0.1.dist-info/WHEEL
czech_air_quality-2.0.1.dist-info/top_level.txt
czech_air_quality-2.0.1.dist-info/RECORD
