Metadata-Version: 2.4
Name: czech_air_quality
Version: 2.0.1
Summary: A python library for retrieving and parsing air quality data from the CHMI opendata portal.
Author-email: chickendrop89 <chickendrop89@gmail.com>
License:                    GNU LESSER GENERAL PUBLIC LICENSE
Project-URL: Repository, https://github.com/chickendrop89/czech_air_quality
Project-URL: Issues, https://github.com/chickendrop89/czech_air_quality/issues
Project-URL: Changelog, https://github.com/chickendrop89/czech_air_quality/blob/master/CHANGELOG.md
Project-URL: Homepage, https://czech-air-quality.readthedocs.io
Keywords: air-quality,chmi,czechia,pollution,aqi,eaqi,geopy,isko
Classifier: Programming Language :: Python :: 3
Classifier: Development Status :: 5 - Production/Stable
Classifier: Intended Audience :: Developers
Classifier: Operating System :: OS Independent
Classifier: License :: OSI Approved :: GNU Lesser General Public License v3 (LGPLv3)
Classifier: Topic :: Software Development :: Libraries :: Python Modules
Classifier: Topic :: Scientific/Engineering :: Atmospheric Science
Classifier: Topic :: Internet :: WWW/HTTP
Classifier: Typing :: Typed
Requires-Python: >=3.10
License-File: LICENSE
Requires-Dist: requests>=2.28.0
Requires-Dist: geopy>=2.3.0
Provides-Extra: dev
Requires-Dist: pytest>=9.0.1; extra == "dev"
Requires-Dist: coverage>=7.11.3; extra == "dev"
Requires-Dist: pylint>=4.0.3; extra == "dev"
Provides-Extra: docs
Requires-Dist: sphinx>=7.0.0; extra == "docs"
Requires-Dist: sphinx-rtd-theme>=2.0.0; extra == "docs"
Requires-Dist: sphinx-autodoc-typehints>=1.25.0; extra == "docs"
Dynamic: license-file
